f3ast/__init__.py
f3ast/branches.py
f3ast/deposit_model.py
f3ast/plotting.py
f3ast/resistance.py
f3ast/slicing.py
f3ast/solver.py
f3ast/stream.py
f3ast/stream_builder.py
f3ast/structure.py
f3ast/utils.py
f3ast/version.py
f3ast/calibration/__init__.py
f3ast/calibration/picture_processing.py
f3ast/calibration/set_scale.py
f3ast/calibration/sigma_structures.py
f3ast/calibration/vertical_structures.py
f3ast-1.0.1.dist-info/LICENSE
f3ast-1.0.1.dist-info/METADATA
f3ast-1.0.1.dist-info/WHEEL
f3ast-1.0.1.dist-info/top_level.txt
f3ast-1.0.1.dist-info/RECORD
