Metadata-Version: 2.1
Name: f3ast
Version: 1.0.1
Summary: FEBID 3D Algorithm for Stream File Generation (F3AST)
Author: Luka Skoric
License: GNU GENERAL PUBLIC LICENSE
License-File: LICENSE
Requires-Dist: trimesh (>=3.9.12)
Requires-Dist: numpy (>=1.20.2)
Requires-Dist: matplotlib (>=3.4.1)
Requires-Dist: hjson (>=3.0.2)
Requires-Dist: numba (>=0.53.1)
Requires-Dist: joblib (>=1.0.1)
Requires-Dist: PyQt5 (>=5.15.4)
Requires-Dist: scikit-image (>=0.18.1)
Requires-Dist: scipy (>=1.6.2)
Requires-Dist: tbb (>=2021.2.0)
Requires-Dist: pyglet (>=1.5.16)
Requires-Dist: pytest (>=7.1.3)
